{
  "parent": "minecraft:recipes/root",
  "rewards": {
    "recipes": [
      "lightland:mortar/white_rice"
    ]
  },
  "criteria": {
    "has_rice": {
      "trigger": "minecraft:inventory_changed",
      "conditions": {
        "items": [
          {
            "items": [
              "lightland:rice"
            ]
          }
        ]
      }
    },
    "has_the_recipe": {
      "trigger": "minecraft:recipe_unlocked",
      "conditions": {
        "recipe": "lightland:mortar/white_rice"
      }
    }
  },
  "requirements": [
    [
      "has_rice",
      "has_the_recipe"
    ]
  ]
}